analytixhero/__init__.py
analytixhero/_basic_functions.py
analytixhero/_combine_and_split.py
analytixhero/_eda.py
analytixhero/_encoding.py
analytixhero/_information.py
analytixhero/_null.py
analytixhero/_outliers.py
analytixhero/_transformation.py
analytixhero-0.0.1.dist-info/LICENSE
analytixhero-0.0.1.dist-info/METADATA
analytixhero-0.0.1.dist-info/WHEEL
analytixhero-0.0.1.dist-info/top_level.txt
analytixhero-0.0.1.dist-info/RECORD
