Metadata-Version: 2.1
Name: analytixhero
Version: 0.0.1
Summary: Everything That Needs To Be Done While Preprocessing Data, May It Be Outlier Handling, Skewness/Kurtosis Minimization, Treating Null Spaces Etc. Can Be Done With Pre-Defined State-Of-Art Features.
Home-page: https://github.com/thesahibnanda/AnalytiXHero
Author: Sahib Nanda
Author-email: <essenbeats@gmail.com>
License: BSD
Project-URL: Documentation, https://github.com/thesahibnanda/AnalytiXHero/blob/main/DOCUMENTATION/0.%20Documentation%20Index.md
Project-URL: Source Code, https://github.com/thesahibnanda/AnalytiXHero
Classifier: Development Status :: 3 - Alpha
Classifier: Intended Audience :: Developers
Classifier: Programming Language :: Python :: 3
Classifier: Operating System :: Unix
Classifier: Operating System :: MacOS :: MacOS X
Classifier: Operating System :: Microsoft :: Windows
Classifier: License :: OSI Approved :: BSD License
License-File: LICENSE
Requires-Dist: numpy (>=1.22.3)
Requires-Dist: pandas (>=2.0.0)
Requires-Dist: scikit-learn (>=1.0.0)
Requires-Dist: scipy (>=1.10.0)
Requires-Dist: matplotlib (>=3.5.0)
Requires-Dist: seaborn (>=0.11)
Requires-Dist: python-dateutil (>=2.8.0)
